{
  "kind": "Root",
  "name": "TopLevel",
  "printedName": "TopLevel",
  "children": [
    {
      "kind": "Import",
      "name": "Foundation",
      "printedName": "Foundation",
      "declKind": "Import",
      "moduleName": "Simple"
    },
    {
      "kind": "Function",
      "name": "startingSenario",
      "printedName": "startingSenario()",
      "children": [
        {
          "kind": "TypeNominal",
          "name": "Void",
          "printedName": "()"
        }
      ],
      "declKind": "Func",
      "usr": "s:6Simple15startingSenarioyyF",
      "mangledName": "$s6Simple15startingSenarioyyF",
      "moduleName": "Simple",
      "funcSelfKind": "NonMutating"
    },
    {
      "kind": "Function",
      "name": "instructions",
      "printedName": "instructions()",
      "children": [
        {
          "kind": "TypeNominal",
          "name": "Void",
          "printedName": "()"
        }
      ],
      "declKind": "Func",
      "usr": "s:6Simple12instructionsyyF",
      "mangledName": "$s6Simple12instructionsyyF",
      "moduleName": "Simple",
      "funcSelfKind": "NonMutating"
    },
    {
      "kind": "Var",
      "name": "name",
      "printedName": "name",
      "children": [
        {
          "kind": "TypeNominal",
          "name": "String",
          "printedName": "Swift.String",
          "usr": "s:SS"
        }
      ],
      "declKind": "Var",
      "usr": "s:6Simple4nameSSvp",
      "mangledName": "$s6Simple4nameSSvp",
      "moduleName": "Simple",
      "declAttributes": [
        "HasInitialValue",
        "HasStorage"
      ],
      "hasStorage": true
    },
    {
      "kind": "Function",
      "name": "getName",
      "printedName": "getName()",
      "children": [
        {
          "kind": "TypeNominal",
          "name": "Void",
          "printedName": "()"
        }
      ],
      "declKind": "Func",
      "usr": "s:6Simple7getNameyyF",
      "mangledName": "$s6Simple7getNameyyF",
      "moduleName": "Simple",
      "funcSelfKind": "NonMutating"
    },
    {
      "kind": "Var",
      "name": "Friend1",
      "printedName": "Friend1",
      "children": [
        {
          "kind": "TypeNominal",
          "name": "String",
          "printedName": "Swift.String",
          "usr": "s:SS"
        }
      ],
      "declKind": "Var",
      "usr": "s:6Simple7Friend1SSvp",
      "mangledName": "$s6Simple7Friend1SSvp",
      "moduleName": "Simple",
      "declAttributes": [
        "HasInitialValue",
        "HasStorage"
      ],
      "hasStorage": true
    },
    {
      "kind": "Var",
      "name": "Friend2",
      "printedName": "Friend2",
      "children": [
        {
          "kind": "TypeNominal",
          "name": "String",
          "printedName": "Swift.String",
          "usr": "s:SS"
        }
      ],
      "declKind": "Var",
      "usr": "s:6Simple7Friend2SSvp",
      "mangledName": "$s6Simple7Friend2SSvp",
      "moduleName": "Simple",
      "declAttributes": [
        "HasInitialValue",
        "HasStorage"
      ],
      "hasStorage": true
    },
    {
      "kind": "Var",
      "name": "Friend3",
      "printedName": "Friend3",
      "children": [
        {
          "kind": "TypeNominal",
          "name": "String",
          "printedName": "Swift.String",
          "usr": "s:SS"
        }
      ],
      "declKind": "Var",
      "usr": "s:6Simple7Friend3SSvp",
      "mangledName": "$s6Simple7Friend3SSvp",
      "moduleName": "Simple",
      "declAttributes": [
        "HasInitialValue",
        "HasStorage"
      ],
      "hasStorage": true
    },
    {
      "kind": "Function",
      "name": "getNameOfFriends",
      "printedName": "getNameOfFriends()",
      "children": [
        {
          "kind": "TypeNominal",
          "name": "Void",
          "printedName": "()"
        }
      ],
      "declKind": "Func",
      "usr": "s:6Simple16getNameOfFriendsyyF",
      "mangledName": "$s6Simple16getNameOfFriendsyyF",
      "moduleName": "Simple",
      "funcSelfKind": "NonMutating"
    },
    {
      "kind": "Var",
      "name": "choice1",
      "printedName": "choice1",
      "children": [
        {
          "kind": "TypeNominal",
          "name": "String",
          "printedName": "Swift.String",
          "usr": "s:SS"
        }
      ],
      "declKind": "Var",
      "usr": "s:6Simple7choice1SSvp",
      "mangledName": "$s6Simple7choice1SSvp",
      "moduleName": "Simple",
      "declAttributes": [
        "HasInitialValue",
        "HasStorage"
      ],
      "hasStorage": true
    },
    {
      "kind": "Function",
      "name": "scene1",
      "printedName": "scene1()",
      "children": [
        {
          "kind": "TypeNominal",
          "name": "Void",
          "printedName": "()"
        }
      ],
      "declKind": "Func",
      "usr": "s:6Simple6scene1yyF",
      "mangledName": "$s6Simple6scene1yyF",
      "moduleName": "Simple",
      "funcSelfKind": "NonMutating"
    },
    {
      "kind": "Var",
      "name": "choice2",
      "printedName": "choice2",
      "children": [
        {
          "kind": "TypeNominal",
          "name": "String",
          "printedName": "Swift.String",
          "usr": "s:SS"
        }
      ],
      "declKind": "Var",
      "usr": "s:6Simple7choice2SSvp",
      "mangledName": "$s6Simple7choice2SSvp",
      "moduleName": "Simple",
      "declAttributes": [
        "HasInitialValue",
        "HasStorage"
      ],
      "hasStorage": true
    },
    {
      "kind": "Function",
      "name": "scene2",
      "printedName": "scene2()",
      "children": [
        {
          "kind": "TypeNominal",
          "name": "Void",
          "printedName": "()"
        }
      ],
      "declKind": "Func",
      "usr": "s:6Simple6scene2yyF",
      "mangledName": "$s6Simple6scene2yyF",
      "moduleName": "Simple",
      "funcSelfKind": "NonMutating"
    },
    {
      "kind": "Var",
      "name": "choice3",
      "printedName": "choice3",
      "children": [
        {
          "kind": "TypeNominal",
          "name": "String",
          "printedName": "Swift.String",
          "usr": "s:SS"
        }
      ],
      "declKind": "Var",
      "usr": "s:6Simple7choice3SSvp",
      "mangledName": "$s6Simple7choice3SSvp",
      "moduleName": "Simple",
      "declAttributes": [
        "HasInitialValue",
        "HasStorage"
      ],
      "hasStorage": true
    },
    {
      "kind": "Function",
      "name": "scene3",
      "printedName": "scene3()",
      "children": [
        {
          "kind": "TypeNominal",
          "name": "Void",
          "printedName": "()"
        }
      ],
      "declKind": "Func",
      "usr": "s:6Simple6scene3yyF",
      "mangledName": "$s6Simple6scene3yyF",
      "moduleName": "Simple",
      "funcSelfKind": "NonMutating"
    },
    {
      "kind": "Var",
      "name": "choice4",
      "printedName": "choice4",
      "children": [
        {
          "kind": "TypeNominal",
          "name": "String",
          "printedName": "Swift.String",
          "usr": "s:SS"
        }
      ],
      "declKind": "Var",
      "usr": "s:6Simple7choice4SSvp",
      "mangledName": "$s6Simple7choice4SSvp",
      "moduleName": "Simple",
      "declAttributes": [
        "HasInitialValue",
        "HasStorage"
      ],
      "hasStorage": true
    },
    {
      "kind": "Function",
      "name": "scene4",
      "printedName": "scene4()",
      "children": [
        {
          "kind": "TypeNominal",
          "name": "Void",
          "printedName": "()"
        }
      ],
      "declKind": "Func",
      "usr": "s:6Simple6scene4yyF",
      "mangledName": "$s6Simple6scene4yyF",
      "moduleName": "Simple",
      "funcSelfKind": "NonMutating"
    },
    {
      "kind": "Var",
      "name": "endingChoice",
      "printedName": "endingChoice",
      "children": [
        {
          "kind": "TypeNominal",
          "name": "String",
          "printedName": "Swift.String",
          "usr": "s:SS"
        }
      ],
      "declKind": "Var",
      "usr": "s:6Simple12endingChoiceSSvp",
      "mangledName": "$s6Simple12endingChoiceSSvp",
      "moduleName": "Simple",
      "declAttributes": [
        "HasInitialValue",
        "HasStorage"
      ],
      "hasStorage": true
    },
    {
      "kind": "Function",
      "name": "scene5",
      "printedName": "scene5()",
      "children": [
        {
          "kind": "TypeNominal",
          "name": "Void",
          "printedName": "()"
        }
      ],
      "declKind": "Func",
      "usr": "s:6Simple6scene5yyF",
      "mangledName": "$s6Simple6scene5yyF",
      "moduleName": "Simple",
      "funcSelfKind": "NonMutating"
    },
    {
      "kind": "Function",
      "name": "ending",
      "printedName": "ending()",
      "children": [
        {
          "kind": "TypeNominal",
          "name": "Void",
          "printedName": "()"
        }
      ],
      "declKind": "Func",
      "usr": "s:6Simple6endingyyF",
      "mangledName": "$s6Simple6endingyyF",
      "moduleName": "Simple",
      "funcSelfKind": "NonMutating"
    }
  ],
  "json_format_version": 6
}